customs_dtoc/__init__.py
customs_dtoc/csf/__init__.py
customs_dtoc/csf/csf.py
customs_dtoc/landed_cost/__init__.py
customs_dtoc/landed_cost/components_of_lc/__init__.py
customs_dtoc/landed_cost/components_of_lc/ac/__init__.py
customs_dtoc/landed_cost/components_of_lc/ac/outports/__init__.py
customs_dtoc/landed_cost/components_of_lc/ac/outports/ac_outports.py
customs_dtoc/landed_cost/components_of_lc/ac/pom_micp/__init__.py
customs_dtoc/landed_cost/components_of_lc/ac/pom_micp/containerized_dangerous_cargo/20_footer_rates.json
customs_dtoc/landed_cost/components_of_lc/ac/pom_micp/containerized_dangerous_cargo/40_footer_rates.json
customs_dtoc/landed_cost/components_of_lc/ac/pom_micp/containerized_dangerous_cargo/__init__.py
customs_dtoc/landed_cost/components_of_lc/ac/pom_micp/containerized_dangerous_cargo/containerized_dangerous_cargo.py
customs_dtoc/landed_cost/components_of_lc/ac/pom_micp/fcl/__init__.py
customs_dtoc/landed_cost/components_of_lc/ac/pom_micp/fcl/containerized_cargo.py
customs_dtoc/landed_cost/components_of_lc/ac/pom_micp/fcl/export_rates.json
customs_dtoc/landed_cost/components_of_lc/ac/pom_micp/fcl/import_rates.json
customs_dtoc/landed_cost/components_of_lc/ac/pom_micp/fcl/shutout_export_rates.json
customs_dtoc/landed_cost/components_of_lc/ac/pom_micp/lcl/__init__.py
customs_dtoc/landed_cost/components_of_lc/ac/pom_micp/lcl/bulk_break_bulk_cargo.py
customs_dtoc/landed_cost/components_of_lc/ac/pom_micp/lcl/export_rates.json
customs_dtoc/landed_cost/components_of_lc/ac/pom_micp/lcl/import_rates.json
customs_dtoc/landed_cost/components_of_lc/bc/__init__.py
customs_dtoc/landed_cost/components_of_lc/bc/bc.py
customs_dtoc/landed_cost/components_of_lc/bf/__init__.py
customs_dtoc/landed_cost/components_of_lc/bf/bf_formal_entry.py
customs_dtoc/landed_cost/components_of_lc/cds/__init__.py
customs_dtoc/landed_cost/components_of_lc/cds/cds.py
customs_dtoc/landed_cost/components_of_lc/cud/__init__.py
customs_dtoc/landed_cost/components_of_lc/cud/cud.py
customs_dtoc-0.0.9.dist-info/LICENSE
customs_dtoc-0.0.9.dist-info/METADATA
customs_dtoc-0.0.9.dist-info/WHEEL
customs_dtoc-0.0.9.dist-info/top_level.txt
customs_dtoc-0.0.9.dist-info/RECORD
