Metadata-Version: 2.1
Name: customs-dtoc
Version: 0.0.9
Summary: A package for calculating customs duties, taxes, and other charges.
Home-page: https://github.com/iaaan05/python-customs-tax-package
Author: Iaaan05
Author-email: iaaan100500@gmail.com
License: MIT
Keywords: customs,duties,taxes,charges
Classifier: Intended Audience :: Information Technology
Classifier: Intended Audience :: Financial and Insurance Industry
Classifier: License :: OSI Approved :: MIT License
Classifier: Natural Language :: English
Classifier: Operating System :: OS Independent
Classifier: Programming Language :: Python :: 3.11
Requires-Python: >=3.11
License-File: LICENSE
